wonderparse/__init__.py
wonderparse/_autosaving_utils.py
wonderparse/_parameter_utils.py
wonderparse/argumentDict.py
wonderparse/argumentsDict.py
wonderparse/autosaving.py
wonderparse/easymode.py
wonderparse/execution.py
wonderparse/option_string.py
wonderparse/parser.py
wonderparse/process_namespace.py
wonderparse-1.4.1.dist-info/LICENSE.txt
wonderparse-1.4.1.dist-info/METADATA
wonderparse-1.4.1.dist-info/WHEEL
wonderparse-1.4.1.dist-info/top_level.txt
wonderparse-1.4.1.dist-info/RECORD
