Metadata-Version: 2.1
Name: wonderparse
Version: 1.4.1
Summary: easy cooperation between main-function and argparse
Author-email: Johannes <johannes-programming@posteo.org>
License: Copyright © 2023 Johannes
Project-URL: Source, https://github.com/johannes-programming/wonderparse
Project-URL: Download, https://pypi.org/project/wonderparse/#files
Classifier: License :: OSI Approved :: MIT License
Classifier: Programming Language :: Python
Classifier: Programming Language :: Python :: 3
Requires-Python: >=3.11
License-File: LICENSE.txt
Requires-Dist: funcinputs >=1.0
